cpmixer/__init__.py
cpmixer/darwin.py
cpmixer/linux.py
cpmixer/template.py
cpmixer/windows.py
cpmixer-0.8.1.dist-info/LICENSE
cpmixer-0.8.1.dist-info/METADATA
cpmixer-0.8.1.dist-info/WHEEL
cpmixer-0.8.1.dist-info/top_level.txt
cpmixer-0.8.1.dist-info/RECORD
